vibe_widget/__init__.py
vibe_widget/api.py
vibe_widget/config.py
vibe_widget/debug.py
vibe_widget/models_manifest.json
vibe_widget/namespaces.py
vibe_widget/themes.py
vibe_widget/AppWrapper/AppWrapper.editor.bundle.js
vibe_widget/AppWrapper/AppWrapper.js
vibe_widget/AppWrapper/actions/modelActions.js
vibe_widget/AppWrapper/components/AttachmentStrip.js
vibe_widget/AppWrapper/components/AuditNotice.js
vibe_widget/AppWrapper/components/EditPromptPanel.js
vibe_widget/AppWrapper/components/FloatingMenu.js
vibe_widget/AppWrapper/components/LoadingOverlay.js
vibe_widget/AppWrapper/components/ProgressMap.js
vibe_widget/AppWrapper/components/RuntimePanel.js
vibe_widget/AppWrapper/components/SandboxedRunner.js
vibe_widget/AppWrapper/components/SaveDialog.js
vibe_widget/AppWrapper/components/SelectionOverlay.js
vibe_widget/AppWrapper/components/StatePromptInputRow.js
vibe_widget/AppWrapper/components/StateViewer.js
vibe_widget/AppWrapper/components/TerminalViewer.js
vibe_widget/AppWrapper/components/WidgetViewer.js
vibe_widget/AppWrapper/components/editor/AuditPanel.js
vibe_widget/AppWrapper/components/editor/CodeEditor.js
vibe_widget/AppWrapper/components/editor/EditorHeader.js
vibe_widget/AppWrapper/components/editor/EditorViewer.js
vibe_widget/AppWrapper/components/editor/MessageEditor.js
vibe_widget/AppWrapper/editor/EditorBundleEntry.js
vibe_widget/AppWrapper/editor/editorBundleLoader.js
vibe_widget/AppWrapper/hooks/useAuditFlow.js
vibe_widget/AppWrapper/hooks/useCodeFlow.js
vibe_widget/AppWrapper/hooks/useContainerMetrics.js
vibe_widget/AppWrapper/hooks/useGrabEdit.js
vibe_widget/AppWrapper/hooks/useKeyboardShortcuts.js
vibe_widget/AppWrapper/hooks/useModelSync.js
vibe_widget/AppWrapper/styles/setup.js
vibe_widget/AppWrapper/styles/twind.config.js
vibe_widget/AppWrapper/utils/debug.js
vibe_widget/AppWrapper/utils/dom.ts
vibe_widget/AppWrapper/utils/runtimeError.js
vibe_widget/AppWrapper/utils/stackSummary.js
vibe_widget/AppWrapper/utils/styles.ts
vibe_widget-0.2.6.dist-info/METADATA
vibe_widget-0.2.6.dist-info/WHEEL
vibe_widget-0.2.6.dist-info/licenses/LICENSE
vibe_widget-0.2.6.dist-info/RECORD
