Metadata-Version: 2.4
Name: vibe_widget
Version: 0.2.6
Summary: Create interactive visualizations using natural language and LLMs
Project-URL: Homepage, https://vibewidget.dev
Project-URL: Documentation, https://vibewidget.dev
Project-URL: Repository, https://github.com/dwootton/vibe-widget
Project-URL: Issues, https://github.com/dwootton/vibe-widget/issues
Author: Ryan Yen
Author-email: Dylan Wootton <dwootton@mit.edu>
License: MIT
License-File: LICENSE
Keywords: interactive,jupyter,llm,visualization,widgets
Classifier: Development Status :: 3 - Alpha
Classifier: Intended Audience :: Developers
Classifier: Intended Audience :: Science/Research
Classifier: License :: OSI Approved :: MIT License
Classifier: Programming Language :: Python :: 3
Classifier: Programming Language :: Python :: 3.9
Classifier: Programming Language :: Python :: 3.10
Classifier: Programming Language :: Python :: 3.11
Classifier: Programming Language :: Python :: 3.12
Classifier: Topic :: Scientific/Engineering :: Visualization
Requires-Python: >=3.9
Requires-Dist: anywidget>=0.9.0
Requires-Dist: openai>=1.50.0
Requires-Dist: pandas>=2.0.0
Requires-Dist: pretty-little-summary
Requires-Dist: requests>=2.32.0
Provides-Extra: dev
Requires-Dist: ipython>=8.12.0; extra == 'dev'
Requires-Dist: mypy>=1.8.0; extra == 'dev'
Requires-Dist: pytest-cov>=4.1.0; extra == 'dev'
Requires-Dist: pytest>=8.0.0; extra == 'dev'
Requires-Dist: python-dotenv>=1.0.0; extra == 'dev'
Requires-Dist: ruff>=0.6.0; extra == 'dev'
